mgoptimization/__init__.py
mgoptimization/hybrids.py
mgoptimization/pso.py
mgoptimization-0.7.dist-info/METADATA
mgoptimization-0.7.dist-info/WHEEL
mgoptimization-0.7.dist-info/licenses/LICENSE
mgoptimization-0.7.dist-info/RECORD
