Metadata-Version: 2.1
Name: mgoptimization
Version: 0.7
Summary: A tool to optimize the generation system of hybrid mini-grids
Project-URL: Homepage, https://github.com/AndreasSahlberg/hybrid-mini-grid-optimization
Project-URL: Bug Tracker, https://github.com/AndreasSahlberg/hybrid-mini-grid-optimization/issues
Author-email: Andreas Sahlberg <asahl@kth.se>
License: MIT License
License-File: LICENSE
Classifier: License :: OSI Approved :: MIT License
Classifier: Operating System :: OS Independent
Classifier: Programming Language :: Python :: 3
Requires-Python: >=3.8
Requires-Dist: hatchling
Requires-Dist: jupyter
Requires-Dist: matplotlib
Requires-Dist: numba
Requires-Dist: numpy
Requires-Dist: pandas
Requires-Dist: pyswarms
Requires-Dist: requests
